audio_recorder_k/__init__.py
audio_recorder_k/main.py
audio_recorder_k-0.1.0.dist-info/METADATA
audio_recorder_k-0.1.0.dist-info/WHEEL
audio_recorder_k-0.1.0.dist-info/top_level.txt
audio_recorder_k-0.1.0.dist-info/RECORD
