Metadata-Version: 2.1
Name: audio-recorder-k
Version: 0.1.0
Summary: A simple Python library for recording audio
Home-page: https://github.com/Keshab-Kumar/audio_recorder
Author: Keshab Kumar
Classifier: Programming Language :: Python :: 3
Classifier: License :: OSI Approved :: MIT License
Classifier: Operating System :: OS Independent
Requires-Python: >=3.6
Requires-Dist: pyaudio
